[
  {
    "startRaw": "20251225183000",
    "stopRaw": "20251225190000",
    "start": "2025-12-26 00:00:00 IST",
    "stop": "2025-12-26 00:30:00 IST",
    "channel": "jio-1370",
    "title": "Bigg Boss Kannada",
    "subTitle": "Contestants from all walks of life compete with each other to win the cash prize while living in the house together under certain rules.",
    "image": "http://imagestataplay.whatsonindia.com/dasimages/genreimage/landscape/1280x720/26D59B8475F7A4100CF9D83FF9194D66FC385A3ET.jpg"
  },
  {
    "startRaw": "20251225190000",
    "stopRaw": "20251225193000",
    "start": "2025-12-26 00:30:00 IST",
    "stop": "2025-12-26 01:00:00 IST",
    "channel": "jio-1370",
    "title": "Sri Gandhada Gudi",
    "subTitle": "Chandana marries into a family with a troubled past in order to escape her fate. However, can she restore the family's hope?",
    "image": "http://imagestataplay.whatsonindia.com/dasimages/genreimage/landscape/1280x720/26D59B8475F7A4100CF9D83FF9194D66FC385A3ET.jpg"
  },
  {
    "startRaw": "20251225193000",
    "stopRaw": "20251225200000",
    "start": "2025-12-26 01:00:00 IST",
    "stop": "2025-12-26 01:30:00 IST",
    "channel": "jio-1370",
    "title": "Muddu Sose",
    "subTitle": "Vidya's dream of becoming a doctor is threatened when her father decides to get her married. Unfortunately, her father-in-law also believes that woman should not pursue education.",
    "image": "http://imagestataplay.whatsonindia.com/dasimages/genreimage/landscape/1280x720/26D59B8475F7A4100CF9D83FF9194D66FC385A3ET.jpg"
  },
  {
    "startRaw": "20251225200000",
    "stopRaw": "20251225203000",
    "start": "2025-12-26 01:30:00 IST",
    "stop": "2025-12-26 02:00:00 IST",
    "channel": "jio-1370",
    "title": "Shiva Shakthi",
    "subTitle": "The Devas plan a lavish wedding ceremony for Lord Shiva and Parvati in honor of their reunion. As all is going on, Diti laments Karambha's passing and swears to get revenge on Parvati.",
    "image": "http://imagestataplay.whatsonindia.com/dasimages/genreimage/landscape/1280x720/26D59B8475F7A4100CF9D83FF9194D66FC385A3ET.jpg"
  },
  {
    "startRaw": "20251225203000",
    "stopRaw": "20251225213000",
    "start": "2025-12-26 02:00:00 IST",
    "stop": "2025-12-26 03:00:00 IST",
    "channel": "jio-1370",
    "title": "Shantam Paapam",
    "subTitle": "Ravi and Ramani, a married couple, go on a family vacation with their kid. However, things take a tragic turn when Ramani and the child suddenly go missing.",
    "image": "http://imagestataplay.whatsonindia.com/dasimages/genreimage/landscape/1280x720/26D59B8475F7A4100CF9D83FF9194D66FC385A3ET.jpg"
  },
  {
    "startRaw": "20251225213000",
    "stopRaw": "20251225220000",
    "start": "2025-12-26 03:00:00 IST",
    "stop": "2025-12-26 03:30:00 IST",
    "channel": "jio-1370",
    "title": "Prema Kavya",
    "subTitle": "Two sisters, Prema and Kavya, are pushed into marriages they don't want. However, they struggle with love and lies as they seek happiness in their relationships.",
    "image": "http://imagestataplay.whatsonindia.com/dasimages/genreimage/landscape/1280x720/26D59B8475F7A4100CF9D83FF9194D66FC385A3ET.jpg"
  },
  {
    "startRaw": "20251225220000",
    "stopRaw": "20251225223000",
    "start": "2025-12-26 03:30:00 IST",
    "stop": "2025-12-26 04:00:00 IST",
    "channel": "jio-1370",
    "title": "Yajamana",
    "subTitle": "A delivery boy, who is burdened with family responsibilities, gets into a contract marriage with Jhansi, a rich woman who despises men.",
    "image": "http://imagestataplay.whatsonindia.com/dasimages/genreimage/landscape/1280x720/26D59B8475F7A4100CF9D83FF9194D66FC385A3ET.jpg"
  },
  {
    "startRaw": "20251225223000",
    "stopRaw": "20251225230000",
    "start": "2025-12-26 04:00:00 IST",
    "stop": "2025-12-26 04:30:00 IST",
    "channel": "jio-1370",
    "title": "Bhagya Lakshmi",
    "subTitle": "Rishi blames Lakshmi for an accident, and she leaves with their daughter. Years later, their children meet, bringing Rishi and Lakshmi back into each other's lives.",
    "image": "http://imagestataplay.whatsonindia.com/dasimages/genreimage/landscape/1280x720/26D59B8475F7A4100CF9D83FF9194D66FC385A3ET.jpg"
  },
  {
    "startRaw": "20251225230000",
    "stopRaw": "20251225233000",
    "start": "2025-12-26 04:30:00 IST",
    "stop": "2025-12-26 05:00:00 IST",
    "channel": "jio-1370",
    "title": "Muddu Sose",
    "subTitle": "Vidya's dream of becoming a doctor is threatened when her father decides to get her married. Unfortunately, her father-in-law also believes that woman should not pursue education.",
    "image": "http://imagestataplay.whatsonindia.com/dasimages/genreimage/landscape/1280x720/26D59B8475F7A4100CF9D83FF9194D66FC385A3ET.jpg"
  },
  {
    "startRaw": "20251225233000",
    "stopRaw": "20251226000000",
    "start": "2025-12-26 05:00:00 IST",
    "stop": "2025-12-26 05:30:00 IST",
    "channel": "jio-1370",
    "title": "Sri Gandhada Gudi",
    "subTitle": "Chandana marries into a family with a troubled past in order to escape her fate. However, can she restore the family's hope?",
    "image": "http://imagestataplay.whatsonindia.com/dasimages/genreimage/landscape/1280x720/26D59B8475F7A4100CF9D83FF9194D66FC385A3ET.jpg"
  },
  {
    "startRaw": "20251226000000",
    "stopRaw": "20251226003000",
    "start": "2025-12-26 05:30:00 IST",
    "stop": "2025-12-26 06:00:00 IST",
    "channel": "jio-1370",
    "title": "Bhargavi LLB",
    "subTitle": "A lawyer fights against a powerful man, unaware that he will be her father-in-law in the future. As the lines blur between family and justice, she quickly finds herself at a crossroads.",
    "image": "http://imagestataplay.whatsonindia.com/dasimages/genreimage/landscape/1280x720/26D59B8475F7A4100CF9D83FF9194D66FC385A3ET.jpg"
  },
  {
    "startRaw": "20251226003000",
    "stopRaw": "20251226010000",
    "start": "2025-12-26 06:00:00 IST",
    "stop": "2025-12-26 06:30:00 IST",
    "channel": "jio-1370",
    "title": "Silli Lalli",
    "subTitle": "Dr Vittal Rao, a doctor, and his politician wife deal with the mundane issues of life and engage in hilarious escapades with the rest of their family.",
    "image": "http://imagestataplay.whatsonindia.com/dasimages/genreimage/landscape/1280x720/26D59B8475F7A4100CF9D83FF9194D66FC385A3ET.jpg"
  },
  {
    "startRaw": "20251226010000",
    "stopRaw": "20251226013000",
    "start": "2025-12-26 06:30:00 IST",
    "stop": "2025-12-26 07:00:00 IST",
    "channel": "jio-1370",
    "title": "Tenali Rama",
    "subTitle": "When Tenali Rama and the rest visit the forest, they come across a shape-shifter that can transform from a tiger to a human.",
    "image": "http://imagestataplay.whatsonindia.com/dasimages/genreimage/landscape/1280x720/26D59B8475F7A4100CF9D83FF9194D66FC385A3ET.jpg"
  },
  {
    "startRaw": "20251226013000",
    "stopRaw": "20251226020000",
    "start": "2025-12-26 07:00:00 IST",
    "stop": "2025-12-26 07:30:00 IST",
    "channel": "jio-1370",
    "title": "Tenali Rama",
    "subTitle": "Krishnadevaraya and his men set out to hunt the shape-shifting tiger. Meanwhile, the queens panic when they are attacked by another tiger.",
    "image": "http://imagestataplay.whatsonindia.com/dasimages/genreimage/landscape/1280x720/26D59B8475F7A4100CF9D83FF9194D66FC385A3ET.jpg"
  },
  {
    "startRaw": "20251226020000",
    "stopRaw": "20251226030000",
    "start": "2025-12-26 07:30:00 IST",
    "stop": "2025-12-26 08:30:00 IST",
    "channel": "jio-1370",
    "title": "Maharshi Darshana",
    "subTitle": "A renowned astrologer offers temple insights, daily horoscopes and live advice, helping viewers navigate life's challenges with wisdom and spiritual guidance.",
    "image": "http://imagestataplay.whatsonindia.com/dasimages/genreimage/landscape/1280x720/26D59B8475F7A4100CF9D83FF9194D66FC385A3ET.jpg"
  },
  {
    "startRaw": "20251226030000",
    "stopRaw": "20251226033000",
    "start": "2025-12-26 08:30:00 IST",
    "stop": "2025-12-26 09:00:00 IST",
    "channel": "jio-1370",
    "title": "Yajamana",
    "subTitle": "A delivery boy, who is burdened with family responsibilities, gets into a contract marriage with Jhansi, a rich woman who despises men.",
    "image": "http://imagestataplay.whatsonindia.com/dasimages/genreimage/landscape/1280x720/26D59B8475F7A4100CF9D83FF9194D66FC385A3ET.jpg"
  },
  {
    "startRaw": "20251226033000",
    "stopRaw": "20251226040000",
    "start": "2025-12-26 09:00:00 IST",
    "stop": "2025-12-26 09:30:00 IST",
    "channel": "jio-1370",
    "title": "Sri Gandhada Gudi",
    "subTitle": "Chandana marries into a family with a troubled past in order to escape her fate. However, can she restore the family's hope?",
    "image": "http://imagestataplay.whatsonindia.com/dasimages/genreimage/landscape/1280x720/26D59B8475F7A4100CF9D83FF9194D66FC385A3ET.jpg"
  },
  {
    "startRaw": "20251226040000",
    "stopRaw": "20251226043000",
    "start": "2025-12-26 09:30:00 IST",
    "stop": "2025-12-26 10:00:00 IST",
    "channel": "jio-1370",
    "title": "Prema Kavya",
    "subTitle": "Two sisters, Prema and Kavya, are pushed into marriages they don't want. However, they struggle with love and lies as they seek happiness in their relationships.",
    "image": "http://imagestataplay.whatsonindia.com/dasimages/genreimage/landscape/1280x720/26D59B8475F7A4100CF9D83FF9194D66FC385A3ET.jpg"
  },
  {
    "startRaw": "20251226043000",
    "stopRaw": "20251226050000",
    "start": "2025-12-26 10:00:00 IST",
    "stop": "2025-12-26 10:30:00 IST",
    "channel": "jio-1370",
    "title": "Bhagya Lakshmi",
    "subTitle": "Rishi blames Lakshmi for an accident, and she leaves with their daughter. Years later, their children meet, bringing Rishi and Lakshmi back into each other's lives.",
    "image": "http://imagestataplay.whatsonindia.com/dasimages/genreimage/landscape/1280x720/26D59B8475F7A4100CF9D83FF9194D66FC385A3ET.jpg"
  },
  {
    "startRaw": "20251226050000",
    "stopRaw": "20251226053000",
    "start": "2025-12-26 10:30:00 IST",
    "stop": "2025-12-26 11:00:00 IST",
    "channel": "jio-1370",
    "title": "Muddu Sose",
    "subTitle": "Vidya's dream of becoming a doctor is threatened when her father decides to get her married. Unfortunately, her father-in-law also believes that woman should not pursue education.",
    "image": "http://imagestataplay.whatsonindia.com/dasimages/genreimage/landscape/1280x720/26D59B8475F7A4100CF9D83FF9194D66FC385A3ET.jpg"
  },
  {
    "startRaw": "20251226053000",
    "stopRaw": "20251226060000",
    "start": "2025-12-26 11:00:00 IST",
    "stop": "2025-12-26 11:30:00 IST",
    "channel": "jio-1370",
    "title": "Nandagokula",
    "subTitle": "Nandakumar shares a close relationship with his family. However, when enemies threaten his loved ones, can he stop his family from breaking apart?",
    "image": "http://imagestataplay.whatsonindia.com/dasimages/genreimage/landscape/1280x720/26D59B8475F7A4100CF9D83FF9194D66FC385A3ET.jpg"
  },
  {
    "startRaw": "20251226060000",
    "stopRaw": "20251226073000",
    "start": "2025-12-26 11:30:00 IST",
    "stop": "2025-12-26 13:00:00 IST",
    "channel": "jio-1370",
    "title": "Bigg Boss Kannada",
    "subTitle": "Contestants from all walks of life compete with each other to win the cash prize while living in the house together under certain rules.",
    "image": "http://imagestataplay.whatsonindia.com/dasimages/genreimage/landscape/1280x720/26D59B8475F7A4100CF9D83FF9194D66FC385A3ET.jpg"
  },
  {
    "startRaw": "20251226073000",
    "stopRaw": "20251226080000",
    "start": "2025-12-26 13:00:00 IST",
    "stop": "2025-12-26 13:30:00 IST",
    "channel": "jio-1370",
    "title": "Maneye Mantralaya",
    "subTitle": "",
    "image": "http://imagestataplay.whatsonindia.com/dasimages/genreimage/landscape/1280x720/26D59B8475F7A4100CF9D83FF9194D66FC385A3ET.jpg"
  },
  {
    "startRaw": "20251226080000",
    "stopRaw": "20251226090000",
    "start": "2025-12-26 13:30:00 IST",
    "stop": "2025-12-26 14:30:00 IST",
    "channel": "jio-1370",
    "title": "Shantam Paapam",
    "subTitle": "Whilst Suma's husband works in a foreign country, she conducts an affair with another man. However, her illicit relations lead to an unwanted pregnancy.",
    "image": "http://imagestataplay.whatsonindia.com/dasimages/genreimage/landscape/1280x720/26D59B8475F7A4100CF9D83FF9194D66FC385A3ET.jpg"
  },
  {
    "startRaw": "20251226090000",
    "stopRaw": "20251226100000",
    "start": "2025-12-26 14:30:00 IST",
    "stop": "2025-12-26 15:30:00 IST",
    "channel": "jio-1370",
    "title": "Shantam Paapam",
    "subTitle": "A compilation of crime stories that depict the gripping real life incidents and sheds light on the victim's battle for justice.",
    "image": "http://imagestataplay.whatsonindia.com/dasimages/genreimage/landscape/1280x720/26D59B8475F7A4100CF9D83FF9194D66FC385A3ET.jpg"
  },
  {
    "startRaw": "20251226100000",
    "stopRaw": "20251226103000",
    "start": "2025-12-26 15:30:00 IST",
    "stop": "2025-12-26 16:00:00 IST",
    "channel": "jio-1370",
    "title": "Bhargavi LLB",
    "subTitle": "A lawyer fights against a powerful man, unaware that he will be her father-in-law in the future. As the lines blur between family and justice, she quickly finds herself at a crossroads.",
    "image": "http://imagestataplay.whatsonindia.com/dasimages/genreimage/landscape/1280x720/26D59B8475F7A4100CF9D83FF9194D66FC385A3ET.jpg"
  },
  {
    "startRaw": "20251226103000",
    "stopRaw": "20251226110000",
    "start": "2025-12-26 16:00:00 IST",
    "stop": "2025-12-26 16:30:00 IST",
    "channel": "jio-1370",
    "title": "Nandagokula",
    "subTitle": "Nandakumar shares a close relationship with his family. However, when enemies threaten his loved ones, can he stop his family from breaking apart?",
    "image": "http://imagestataplay.whatsonindia.com/dasimages/genreimage/landscape/1280x720/26D59B8475F7A4100CF9D83FF9194D66FC385A3ET.jpg"
  },
  {
    "startRaw": "20251226110000",
    "stopRaw": "20251226123000",
    "start": "2025-12-26 16:30:00 IST",
    "stop": "2025-12-26 18:00:00 IST",
    "channel": "jio-1370",
    "title": "Bigg Boss Kannada",
    "subTitle": "Contestants from all walks of life compete with each other to win the cash prize while living in the house together under certain rules.",
    "image": "http://imagestataplay.whatsonindia.com/dasimages/genreimage/landscape/1280x720/26D59B8475F7A4100CF9D83FF9194D66FC385A3ET.jpg"
  },
  {
    "startRaw": "20251226123000",
    "stopRaw": "20251226130000",
    "start": "2025-12-26 18:00:00 IST",
    "stop": "2025-12-26 18:30:00 IST",
    "channel": "jio-1370",
    "title": "Yajamana",
    "subTitle": "A delivery boy, who is burdened with family responsibilities, gets into a contract marriage with Jhansi, a rich woman who despises men.",
    "image": "http://imagestataplay.whatsonindia.com/dasimages/genreimage/landscape/1280x720/26D59B8475F7A4100CF9D83FF9194D66FC385A3ET.jpg"
  },
  {
    "startRaw": "20251226130000",
    "stopRaw": "20251226133000",
    "start": "2025-12-26 18:30:00 IST",
    "stop": "2025-12-26 19:00:00 IST",
    "channel": "jio-1370",
    "title": "Prema Kavya",
    "subTitle": "Two sisters, Prema and Kavya, are pushed into marriages they don't want. However, they struggle with love and lies as they seek happiness in their relationships.",
    "image": "http://imagestataplay.whatsonindia.com/dasimages/genreimage/landscape/1280x720/26D59B8475F7A4100CF9D83FF9194D66FC385A3ET.jpg"
  },
  {
    "startRaw": "20251226133000",
    "stopRaw": "20251226140000",
    "start": "2025-12-26 19:00:00 IST",
    "stop": "2025-12-26 19:30:00 IST",
    "channel": "jio-1370",
    "title": "Bhagya Lakshmi",
    "subTitle": "Rishi blames Lakshmi for an accident, and she leaves with their daughter. Years later, their children meet, bringing Rishi and Lakshmi back into each other's lives.",
    "image": "http://imagestataplay.whatsonindia.com/dasimages/genreimage/landscape/1280x720/26D59B8475F7A4100CF9D83FF9194D66FC385A3ET.jpg"
  },
  {
    "startRaw": "20251226140000",
    "stopRaw": "20251226143000",
    "start": "2025-12-26 19:30:00 IST",
    "stop": "2025-12-26 20:00:00 IST",
    "channel": "jio-1370",
    "title": "Muddu Sose",
    "subTitle": "Vidya's dream of becoming a doctor is threatened when her father decides to get her married. Unfortunately, her father-in-law also believes that woman should not pursue education.",
    "image": "http://imagestataplay.whatsonindia.com/dasimages/genreimage/landscape/1280x720/26D59B8475F7A4100CF9D83FF9194D66FC385A3ET.jpg"
  },
  {
    "startRaw": "20251226143000",
    "stopRaw": "20251226150000",
    "start": "2025-12-26 20:00:00 IST",
    "stop": "2025-12-26 20:30:00 IST",
    "channel": "jio-1370",
    "title": "Sri Gandhada Gudi",
    "subTitle": "Chandana marries into a family with a troubled past in order to escape her fate. However, can she restore the family's hope?",
    "image": "http://imagestataplay.whatsonindia.com/dasimages/genreimage/landscape/1280x720/26D59B8475F7A4100CF9D83FF9194D66FC385A3ET.jpg"
  },
  {
    "startRaw": "20251226150000",
    "stopRaw": "20251226153000",
    "start": "2025-12-26 20:30:00 IST",
    "stop": "2025-12-26 21:00:00 IST",
    "channel": "jio-1370",
    "title": "Bhargavi LLB",
    "subTitle": "A lawyer fights against a powerful man, unaware that he will be her father-in-law in the future. As the lines blur between family and justice, she quickly finds herself at a crossroads.",
    "image": "http://imagestataplay.whatsonindia.com/dasimages/genreimage/landscape/1280x720/26D59B8475F7A4100CF9D83FF9194D66FC385A3ET.jpg"
  },
  {
    "startRaw": "20251226153000",
    "stopRaw": "20251226160000",
    "start": "2025-12-26 21:00:00 IST",
    "stop": "2025-12-26 21:30:00 IST",
    "channel": "jio-1370",
    "title": "Nandagokula",
    "subTitle": "Nandakumar shares a close relationship with his family. However, when enemies threaten his loved ones, can he stop his family from breaking apart?",
    "image": "http://imagestataplay.whatsonindia.com/dasimages/genreimage/landscape/1280x720/26D59B8475F7A4100CF9D83FF9194D66FC385A3ET.jpg"
  },
  {
    "startRaw": "20251226160000",
    "stopRaw": "20251226173000",
    "start": "2025-12-26 21:30:00 IST",
    "stop": "2025-12-26 23:00:00 IST",
    "channel": "jio-1370",
    "title": "Bigg Boss Kannada",
    "subTitle": "Contestants from all walks of life compete with each other to win the cash prize while living in the house together under certain rules.",
    "image": "http://imagestataplay.whatsonindia.com/dasimages/genreimage/landscape/1280x720/26D59B8475F7A4100CF9D83FF9194D66FC385A3ET.jpg"
  },
  {
    "startRaw": "20251226173000",
    "stopRaw": "20251226182959",
    "start": "2025-12-26 23:00:00 IST",
    "stop": "2025-12-26 23:59:59 IST",
    "channel": "jio-1370",
    "title": "Bigg Boss Kannada",
    "subTitle": "Contestants from all walks of life compete with each other to win the cash prize while living in the house together under certain rules.",
    "image": "http://imagestataplay.whatsonindia.com/dasimages/genreimage/landscape/1280x720/26D59B8475F7A4100CF9D83FF9194D66FC385A3ET.jpg"
  },
  {
    "startRaw": "20251226183000",
    "stopRaw": "20251226190000",
    "start": "2025-12-27 00:00:00 IST",
    "stop": "2025-12-27 00:30:00 IST",
    "channel": "jio-1370",
    "title": "Bigg Boss Kannada",
    "subTitle": "Contestants from all walks of life compete with each other to win the cash prize while living in the house together under certain rules.",
    "image": "http://imagestataplay.whatsonindia.com/dasimages/genreimage/landscape/1280x720/26D59B8475F7A4100CF9D83FF9194D66FC385A3ET.jpg"
  },
  {
    "startRaw": "20251226190000",
    "stopRaw": "20251226193000",
    "start": "2025-12-27 00:30:00 IST",
    "stop": "2025-12-27 01:00:00 IST",
    "channel": "jio-1370",
    "title": "Sri Gandhada Gudi",
    "subTitle": "Chandana marries into a family with a troubled past in order to escape her fate. However, can she restore the family's hope?",
    "image": "http://imagestataplay.whatsonindia.com/dasimages/genreimage/landscape/1280x720/26D59B8475F7A4100CF9D83FF9194D66FC385A3ET.jpg"
  },
  {
    "startRaw": "20251226193000",
    "stopRaw": "20251226200000",
    "start": "2025-12-27 01:00:00 IST",
    "stop": "2025-12-27 01:30:00 IST",
    "channel": "jio-1370",
    "title": "Muddu Sose",
    "subTitle": "Vidya's dream of becoming a doctor is threatened when her father decides to get her married. Unfortunately, her father-in-law also believes that woman should not pursue education.",
    "image": "http://imagestataplay.whatsonindia.com/dasimages/genreimage/landscape/1280x720/26D59B8475F7A4100CF9D83FF9194D66FC385A3ET.jpg"
  },
  {
    "startRaw": "20251226200000",
    "stopRaw": "20251226203000",
    "start": "2025-12-27 01:30:00 IST",
    "stop": "2025-12-27 02:00:00 IST",
    "channel": "jio-1370",
    "title": "Shiva Shakthi",
    "subTitle": "A Pandit visits Goddess Parvati's abode to match her kundli with Lord Shiva's and gather details about the Lord's relatives names. Later, Lord Shiva provides a lengthy list of his relatives names, leaving the Pandit astonished.",
    "image": "http://imagestataplay.whatsonindia.com/dasimages/genreimage/landscape/1280x720/26D59B8475F7A4100CF9D83FF9194D66FC385A3ET.jpg"
  },
  {
    "startRaw": "20251226203000",
    "stopRaw": "20251226213000",
    "start": "2025-12-27 02:00:00 IST",
    "stop": "2025-12-27 03:00:00 IST",
    "channel": "jio-1370",
    "title": "Shantam Paapam",
    "subTitle": "Karunya, an aspiring fashion designer, moves to the big city to fulfill her dreams. However, the situation soon takes a deadly turn.",
    "image": "http://imagestataplay.whatsonindia.com/dasimages/genreimage/landscape/1280x720/26D59B8475F7A4100CF9D83FF9194D66FC385A3ET.jpg"
  },
  {
    "startRaw": "20251226213000",
    "stopRaw": "20251226220000",
    "start": "2025-12-27 03:00:00 IST",
    "stop": "2025-12-27 03:30:00 IST",
    "channel": "jio-1370",
    "title": "Prema Kavya",
    "subTitle": "Two sisters, Prema and Kavya, are pushed into marriages they don't want. However, they struggle with love and lies as they seek happiness in their relationships.",
    "image": "http://imagestataplay.whatsonindia.com/dasimages/genreimage/landscape/1280x720/26D59B8475F7A4100CF9D83FF9194D66FC385A3ET.jpg"
  },
  {
    "startRaw": "20251226220000",
    "stopRaw": "20251226223000",
    "start": "2025-12-27 03:30:00 IST",
    "stop": "2025-12-27 04:00:00 IST",
    "channel": "jio-1370",
    "title": "Yajamana",
    "subTitle": "A delivery boy, who is burdened with family responsibilities, gets into a contract marriage with Jhansi, a rich woman who despises men.",
    "image": "http://imagestataplay.whatsonindia.com/dasimages/genreimage/landscape/1280x720/26D59B8475F7A4100CF9D83FF9194D66FC385A3ET.jpg"
  },
  {
    "startRaw": "20251226223000",
    "stopRaw": "20251226230000",
    "start": "2025-12-27 04:00:00 IST",
    "stop": "2025-12-27 04:30:00 IST",
    "channel": "jio-1370",
    "title": "Bhagya Lakshmi",
    "subTitle": "Rishi blames Lakshmi for an accident, and she leaves with their daughter. Years later, their children meet, bringing Rishi and Lakshmi back into each other's lives.",
    "image": "http://imagestataplay.whatsonindia.com/dasimages/genreimage/landscape/1280x720/26D59B8475F7A4100CF9D83FF9194D66FC385A3ET.jpg"
  },
  {
    "startRaw": "20251226230000",
    "stopRaw": "20251226233000",
    "start": "2025-12-27 04:30:00 IST",
    "stop": "2025-12-27 05:00:00 IST",
    "channel": "jio-1370",
    "title": "Muddu Sose",
    "subTitle": "Vidya's dream of becoming a doctor is threatened when her father decides to get her married. Unfortunately, her father-in-law also believes that woman should not pursue education.",
    "image": "http://imagestataplay.whatsonindia.com/dasimages/genreimage/landscape/1280x720/26D59B8475F7A4100CF9D83FF9194D66FC385A3ET.jpg"
  },
  {
    "startRaw": "20251226233000",
    "stopRaw": "20251227000000",
    "start": "2025-12-27 05:00:00 IST",
    "stop": "2025-12-27 05:30:00 IST",
    "channel": "jio-1370",
    "title": "Sri Gandhada Gudi",
    "subTitle": "Chandana marries into a family with a troubled past in order to escape her fate. However, can she restore the family's hope?",
    "image": "http://imagestataplay.whatsonindia.com/dasimages/genreimage/landscape/1280x720/26D59B8475F7A4100CF9D83FF9194D66FC385A3ET.jpg"
  },
  {
    "startRaw": "20251227000000",
    "stopRaw": "20251227003000",
    "start": "2025-12-27 05:30:00 IST",
    "stop": "2025-12-27 06:00:00 IST",
    "channel": "jio-1370",
    "title": "Bhargavi LLB",
    "subTitle": "A lawyer fights against a powerful man, unaware that he will be her father-in-law in the future. As the lines blur between family and justice, she quickly finds herself at a crossroads.",
    "image": "http://imagestataplay.whatsonindia.com/dasimages/genreimage/landscape/1280x720/26D59B8475F7A4100CF9D83FF9194D66FC385A3ET.jpg"
  },
  {
    "startRaw": "20251227003000",
    "stopRaw": "20251227010000",
    "start": "2025-12-27 06:00:00 IST",
    "stop": "2025-12-27 06:30:00 IST",
    "channel": "jio-1370",
    "title": "Silli Lalli",
    "subTitle": "Dr Vittal Rao, a doctor, and his politician wife deal with the mundane issues of life and engage in hilarious escapades with the rest of their family.",
    "image": "http://imagestataplay.whatsonindia.com/dasimages/genreimage/landscape/1280x720/26D59B8475F7A4100CF9D83FF9194D66FC385A3ET.jpg"
  },
  {
    "startRaw": "20251227010000",
    "stopRaw": "20251227013000",
    "start": "2025-12-27 06:30:00 IST",
    "stop": "2025-12-27 07:00:00 IST",
    "channel": "jio-1370",
    "title": "Tenali Rama",
    "subTitle": "Krishnadevaraya and his men are relieved when they manage to capture the shape-shifter. Later, Tenali Rama tries to find out if the man is really a shape-shifter.",
    "image": "http://imagestataplay.whatsonindia.com/dasimages/genreimage/landscape/1280x720/26D59B8475F7A4100CF9D83FF9194D66FC385A3ET.jpg"
  },
  {
    "startRaw": "20251227013000",
    "stopRaw": "20251227020000",
    "start": "2025-12-27 07:00:00 IST",
    "stop": "2025-12-27 07:30:00 IST",
    "channel": "jio-1370",
    "title": "Tenali Rama",
    "subTitle": "Krishnadevaraya questions Lakhna about the myth he created about the man-eating tiger and the latter explains his actions.",
    "image": "http://imagestataplay.whatsonindia.com/dasimages/genreimage/landscape/1280x720/26D59B8475F7A4100CF9D83FF9194D66FC385A3ET.jpg"
  },
  {
    "startRaw": "20251227020000",
    "stopRaw": "20251227030000",
    "start": "2025-12-27 07:30:00 IST",
    "stop": "2025-12-27 08:30:00 IST",
    "channel": "jio-1370",
    "title": "Maharshi Darshana",
    "subTitle": "A renowned astrologer offers temple insights, daily horoscopes and live advice, helping viewers navigate life's challenges with wisdom and spiritual guidance.",
    "image": "http://imagestataplay.whatsonindia.com/dasimages/genreimage/landscape/1280x720/26D59B8475F7A4100CF9D83FF9194D66FC385A3ET.jpg"
  },
  {
    "startRaw": "20251227030000",
    "stopRaw": "20251227033000",
    "start": "2025-12-27 08:30:00 IST",
    "stop": "2025-12-27 09:00:00 IST",
    "channel": "jio-1370",
    "title": "Yajamana",
    "subTitle": "A delivery boy, who is burdened with family responsibilities, gets into a contract marriage with Jhansi, a rich woman who despises men.",
    "image": "http://imagestataplay.whatsonindia.com/dasimages/genreimage/landscape/1280x720/26D59B8475F7A4100CF9D83FF9194D66FC385A3ET.jpg"
  },
  {
    "startRaw": "20251227033000",
    "stopRaw": "20251227040000",
    "start": "2025-12-27 09:00:00 IST",
    "stop": "2025-12-27 09:30:00 IST",
    "channel": "jio-1370",
    "title": "Sri Gandhada Gudi",
    "subTitle": "Chandana marries into a family with a troubled past in order to escape her fate. However, can she restore the family's hope?",
    "image": "http://imagestataplay.whatsonindia.com/dasimages/genreimage/landscape/1280x720/26D59B8475F7A4100CF9D83FF9194D66FC385A3ET.jpg"
  },
  {
    "startRaw": "20251227040000",
    "stopRaw": "20251227043000",
    "start": "2025-12-27 09:30:00 IST",
    "stop": "2025-12-27 10:00:00 IST",
    "channel": "jio-1370",
    "title": "Prema Kavya",
    "subTitle": "Two sisters, Prema and Kavya, are pushed into marriages they don't want. However, they struggle with love and lies as they seek happiness in their relationships.",
    "image": "http://imagestataplay.whatsonindia.com/dasimages/genreimage/landscape/1280x720/26D59B8475F7A4100CF9D83FF9194D66FC385A3ET.jpg"
  },
  {
    "startRaw": "20251227043000",
    "stopRaw": "20251227050000",
    "start": "2025-12-27 10:00:00 IST",
    "stop": "2025-12-27 10:30:00 IST",
    "channel": "jio-1370",
    "title": "Bhagya Lakshmi",
    "subTitle": "Rishi blames Lakshmi for an accident, and she leaves with their daughter. Years later, their children meet, bringing Rishi and Lakshmi back into each other's lives.",
    "image": "http://imagestataplay.whatsonindia.com/dasimages/genreimage/landscape/1280x720/26D59B8475F7A4100CF9D83FF9194D66FC385A3ET.jpg"
  },
  {
    "startRaw": "20251227050000",
    "stopRaw": "20251227053000",
    "start": "2025-12-27 10:30:00 IST",
    "stop": "2025-12-27 11:00:00 IST",
    "channel": "jio-1370",
    "title": "Muddu Sose",
    "subTitle": "Vidya's dream of becoming a doctor is threatened when her father decides to get her married. Unfortunately, her father-in-law also believes that woman should not pursue education.",
    "image": "http://imagestataplay.whatsonindia.com/dasimages/genreimage/landscape/1280x720/26D59B8475F7A4100CF9D83FF9194D66FC385A3ET.jpg"
  },
  {
    "startRaw": "20251227053000",
    "stopRaw": "20251227060000",
    "start": "2025-12-27 11:00:00 IST",
    "stop": "2025-12-27 11:30:00 IST",
    "channel": "jio-1370",
    "title": "Nandagokula",
    "subTitle": "Nandakumar shares a close relationship with his family. However, when enemies threaten his loved ones, can he stop his family from breaking apart?",
    "image": "http://imagestataplay.whatsonindia.com/dasimages/genreimage/landscape/1280x720/26D59B8475F7A4100CF9D83FF9194D66FC385A3ET.jpg"
  },
  {
    "startRaw": "20251227060000",
    "stopRaw": "20251227073000",
    "start": "2025-12-27 11:30:00 IST",
    "stop": "2025-12-27 13:00:00 IST",
    "channel": "jio-1370",
    "title": "Bigg Boss Kannada",
    "subTitle": "Contestants from all walks of life compete with each other to win the cash prize while living in the house together under certain rules.",
    "image": "http://imagestataplay.whatsonindia.com/dasimages/genreimage/landscape/1280x720/26D59B8475F7A4100CF9D83FF9194D66FC385A3ET.jpg"
  },
  {
    "startRaw": "20251227073000",
    "stopRaw": "20251227080000",
    "start": "2025-12-27 13:00:00 IST",
    "stop": "2025-12-27 13:30:00 IST",
    "channel": "jio-1370",
    "title": "Maneye Mantralaya",
    "subTitle": "",
    "image": "http://imagestataplay.whatsonindia.com/dasimages/genreimage/landscape/1280x720/26D59B8475F7A4100CF9D83FF9194D66FC385A3ET.jpg"
  },
  {
    "startRaw": "20251227080000",
    "stopRaw": "20251227110000",
    "start": "2025-12-27 13:30:00 IST",
    "stop": "2025-12-27 16:30:00 IST",
    "channel": "jio-1370",
    "title": "Ganga Yamuna",
    "subTitle": "Greed drives a married woman with children to force her husband into marrying a rich woman. As she enjoys her newfound wealth, she realises that her family find comfort in the company of the new wife.",
    "image": "http://imagestataplay.whatsonindia.com/dasimages/genreimage/landscape/1280x720/26D59B8475F7A4100CF9D83FF9194D66FC385A3ET.jpg"
  },
  {
    "startRaw": "20251227110000",
    "stopRaw": "20251227123000",
    "start": "2025-12-27 16:30:00 IST",
    "stop": "2025-12-27 18:00:00 IST",
    "channel": "jio-1370",
    "title": "Bigg Boss Kannada",
    "subTitle": "Contestants from all walks of life compete with each other to win the cash prize while living in the house together under certain rules.",
    "image": "http://imagestataplay.whatsonindia.com/dasimages/genreimage/landscape/1280x720/26D59B8475F7A4100CF9D83FF9194D66FC385A3ET.jpg"
  },
  {
    "startRaw": "20251227123000",
    "stopRaw": "20251227130000",
    "start": "2025-12-27 18:00:00 IST",
    "stop": "2025-12-27 18:30:00 IST",
    "channel": "jio-1370",
    "title": "Yajamana",
    "subTitle": "A delivery boy, who is burdened with family responsibilities, gets into a contract marriage with Jhansi, a rich woman who despises men.",
    "image": "http://imagestataplay.whatsonindia.com/dasimages/genreimage/landscape/1280x720/26D59B8475F7A4100CF9D83FF9194D66FC385A3ET.jpg"
  },
  {
    "startRaw": "20251227130000",
    "stopRaw": "20251227133000",
    "start": "2025-12-27 18:30:00 IST",
    "stop": "2025-12-27 19:00:00 IST",
    "channel": "jio-1370",
    "title": "Yajamana",
    "subTitle": "A delivery boy, who is burdened with family responsibilities, gets into a contract marriage with Jhansi, a rich woman who despises men.",
    "image": "http://imagestataplay.whatsonindia.com/dasimages/genreimage/landscape/1280x720/26D59B8475F7A4100CF9D83FF9194D66FC385A3ET.jpg"
  },
  {
    "startRaw": "20251227133000",
    "stopRaw": "20251227140000",
    "start": "2025-12-27 19:00:00 IST",
    "stop": "2025-12-27 19:30:00 IST",
    "channel": "jio-1370",
    "title": "Bhagya Lakshmi",
    "subTitle": "Rishi blames Lakshmi for an accident, and she leaves with their daughter. Years later, their children meet, bringing Rishi and Lakshmi back into each other's lives.",
    "image": "http://imagestataplay.whatsonindia.com/dasimages/genreimage/landscape/1280x720/26D59B8475F7A4100CF9D83FF9194D66FC385A3ET.jpg"
  },
  {
    "startRaw": "20251227140000",
    "stopRaw": "20251227143000",
    "start": "2025-12-27 19:30:00 IST",
    "stop": "2025-12-27 20:00:00 IST",
    "channel": "jio-1370",
    "title": "Muddu Sose",
    "subTitle": "Vidya's dream of becoming a doctor is threatened when her father decides to get her married. Unfortunately, her father-in-law also believes that woman should not pursue education.",
    "image": "http://imagestataplay.whatsonindia.com/dasimages/genreimage/landscape/1280x720/26D59B8475F7A4100CF9D83FF9194D66FC385A3ET.jpg"
  },
  {
    "startRaw": "20251227143000",
    "stopRaw": "20251227150000",
    "start": "2025-12-27 20:00:00 IST",
    "stop": "2025-12-27 20:30:00 IST",
    "channel": "jio-1370",
    "title": "Sri Gandhada Gudi",
    "subTitle": "Chandana marries into a family with a troubled past in order to escape her fate. However, can she restore the family's hope?",
    "image": "http://imagestataplay.whatsonindia.com/dasimages/genreimage/landscape/1280x720/26D59B8475F7A4100CF9D83FF9194D66FC385A3ET.jpg"
  },
  {
    "startRaw": "20251227150000",
    "stopRaw": "20251227153000",
    "start": "2025-12-27 20:30:00 IST",
    "stop": "2025-12-27 21:00:00 IST",
    "channel": "jio-1370",
    "title": "Bhargavi LLB",
    "subTitle": "A lawyer fights against a powerful man, unaware that he will be her father-in-law in the future. As the lines blur between family and justice, she quickly finds herself at a crossroads.",
    "image": "http://imagestataplay.whatsonindia.com/dasimages/genreimage/landscape/1280x720/26D59B8475F7A4100CF9D83FF9194D66FC385A3ET.jpg"
  },
  {
    "startRaw": "20251227153000",
    "stopRaw": "20251227173000",
    "start": "2025-12-27 21:00:00 IST",
    "stop": "2025-12-27 23:00:00 IST",
    "channel": "jio-1370",
    "title": "Bigg Boss Kannada",
    "subTitle": "Contestants from all walks of life compete with each other to win the cash prize while living in the house together under certain rules.",
    "image": "http://imagestataplay.whatsonindia.com/dasimages/genreimage/landscape/1280x720/26D59B8475F7A4100CF9D83FF9194D66FC385A3ET.jpg"
  },
  {
    "startRaw": "20251227173000",
    "stopRaw": "20251227182959",
    "start": "2025-12-27 23:00:00 IST",
    "stop": "2025-12-27 23:59:59 IST",
    "channel": "jio-1370",
    "title": "Bigg Boss Kannada",
    "subTitle": "Contestants from all walks of life compete with each other to win the cash prize while living in the house together under certain rules.",
    "image": "http://imagestataplay.whatsonindia.com/dasimages/genreimage/landscape/1280x720/26D59B8475F7A4100CF9D83FF9194D66FC385A3ET.jpg"
  },
  {
    "startRaw": "20251227183000",
    "stopRaw": "20251227193000",
    "start": "2025-12-28 00:00:00 IST",
    "stop": "2025-12-28 01:00:00 IST",
    "channel": "jio-1370",
    "title": "Bigg Boss Kannada",
    "subTitle": "Contestants from all walks of life compete with each other to win the cash prize while living in the house together under certain rules.",
    "image": "http://imagestataplay.whatsonindia.com/dasimages/genreimage/landscape/1280x720/26D59B8475F7A4100CF9D83FF9194D66FC385A3ET.jpg"
  },
  {
    "startRaw": "20251227193000",
    "stopRaw": "20251227200000",
    "start": "2025-12-28 01:00:00 IST",
    "stop": "2025-12-28 01:30:00 IST",
    "channel": "jio-1370",
    "title": "Muddu Sose",
    "subTitle": "Vidya's dream of becoming a doctor is threatened when her father decides to get her married. Unfortunately, her father-in-law also believes that woman should not pursue education.",
    "image": "http://imagestataplay.whatsonindia.com/dasimages/genreimage/landscape/1280x720/26D59B8475F7A4100CF9D83FF9194D66FC385A3ET.jpg"
  },
  {
    "startRaw": "20251227200000",
    "stopRaw": "20251227203000",
    "start": "2025-12-28 01:30:00 IST",
    "stop": "2025-12-28 02:00:00 IST",
    "channel": "jio-1370",
    "title": "Shiva Shakthi",
    "subTitle": "Tarakasura, disguising himself as a messenger from Himavan, confronts Lord Shiva. With malicious intent, he hatches a scheme to sabotage the impending wedding of Lord Shiva and Parvati. Will his evil plot succeed?",
    "image": "http://imagestataplay.whatsonindia.com/dasimages/genreimage/landscape/1280x720/26D59B8475F7A4100CF9D83FF9194D66FC385A3ET.jpg"
  },
  {
    "startRaw": "20251227203000",
    "stopRaw": "20251227213000",
    "start": "2025-12-28 02:00:00 IST",
    "stop": "2025-12-28 03:00:00 IST",
    "channel": "jio-1370",
    "title": "Shantam Paapam",
    "subTitle": "Sandeepa has flaws that cannot be masked with his various successes. Subsequently, his life unravels when his affair is unveiled.",
    "image": "http://imagestataplay.whatsonindia.com/dasimages/genreimage/landscape/1280x720/26D59B8475F7A4100CF9D83FF9194D66FC385A3ET.jpg"
  },
  {
    "startRaw": "20251227213000",
    "stopRaw": "20251227220000",
    "start": "2025-12-28 03:00:00 IST",
    "stop": "2025-12-28 03:30:00 IST",
    "channel": "jio-1370",
    "title": "Yajamana",
    "subTitle": "A delivery boy, who is burdened with family responsibilities, gets into a contract marriage with Jhansi, a rich woman who despises men.",
    "image": "http://imagestataplay.whatsonindia.com/dasimages/genreimage/landscape/1280x720/26D59B8475F7A4100CF9D83FF9194D66FC385A3ET.jpg"
  },
  {
    "startRaw": "20251227220000",
    "stopRaw": "20251227223000",
    "start": "2025-12-28 03:30:00 IST",
    "stop": "2025-12-28 04:00:00 IST",
    "channel": "jio-1370",
    "title": "Yajamana",
    "subTitle": "A delivery boy, who is burdened with family responsibilities, gets into a contract marriage with Jhansi, a rich woman who despises men.",
    "image": "http://imagestataplay.whatsonindia.com/dasimages/genreimage/landscape/1280x720/26D59B8475F7A4100CF9D83FF9194D66FC385A3ET.jpg"
  },
  {
    "startRaw": "20251227223000",
    "stopRaw": "20251227230000",
    "start": "2025-12-28 04:00:00 IST",
    "stop": "2025-12-28 04:30:00 IST",
    "channel": "jio-1370",
    "title": "Bhagya Lakshmi",
    "subTitle": "Rishi blames Lakshmi for an accident, and she leaves with their daughter. Years later, their children meet, bringing Rishi and Lakshmi back into each other's lives.",
    "image": "http://imagestataplay.whatsonindia.com/dasimages/genreimage/landscape/1280x720/26D59B8475F7A4100CF9D83FF9194D66FC385A3ET.jpg"
  },
  {
    "startRaw": "20251227230000",
    "stopRaw": "20251227233000",
    "start": "2025-12-28 04:30:00 IST",
    "stop": "2025-12-28 05:00:00 IST",
    "channel": "jio-1370",
    "title": "Muddu Sose",
    "subTitle": "Vidya's dream of becoming a doctor is threatened when her father decides to get her married. Unfortunately, her father-in-law also believes that woman should not pursue education.",
    "image": "http://imagestataplay.whatsonindia.com/dasimages/genreimage/landscape/1280x720/26D59B8475F7A4100CF9D83FF9194D66FC385A3ET.jpg"
  },
  {
    "startRaw": "20251227233000",
    "stopRaw": "20251228000000",
    "start": "2025-12-28 05:00:00 IST",
    "stop": "2025-12-28 05:30:00 IST",
    "channel": "jio-1370",
    "title": "Sri Gandhada Gudi",
    "subTitle": "Chandana marries into a family with a troubled past in order to escape her fate. However, can she restore the family's hope?",
    "image": "http://imagestataplay.whatsonindia.com/dasimages/genreimage/landscape/1280x720/26D59B8475F7A4100CF9D83FF9194D66FC385A3ET.jpg"
  },
  {
    "startRaw": "20251228000000",
    "stopRaw": "20251228003000",
    "start": "2025-12-28 05:30:00 IST",
    "stop": "2025-12-28 06:00:00 IST",
    "channel": "jio-1370",
    "title": "Bhargavi LLB",
    "subTitle": "A lawyer fights against a powerful man, unaware that he will be her father-in-law in the future. As the lines blur between family and justice, she quickly finds herself at a crossroads.",
    "image": "http://imagestataplay.whatsonindia.com/dasimages/genreimage/landscape/1280x720/26D59B8475F7A4100CF9D83FF9194D66FC385A3ET.jpg"
  },
  {
    "startRaw": "20251228003000",
    "stopRaw": "20251228010000",
    "start": "2025-12-28 06:00:00 IST",
    "stop": "2025-12-28 06:30:00 IST",
    "channel": "jio-1370",
    "title": "Silli Lalli",
    "subTitle": "Dr Vittal Rao, a doctor, and his politician wife deal with the mundane issues of life and engage in hilarious escapades with the rest of their family.",
    "image": "http://imagestataplay.whatsonindia.com/dasimages/genreimage/landscape/1280x720/26D59B8475F7A4100CF9D83FF9194D66FC385A3ET.jpg"
  },
  {
    "startRaw": "20251228010000",
    "stopRaw": "20251228013000",
    "start": "2025-12-28 06:30:00 IST",
    "stop": "2025-12-28 07:00:00 IST",
    "channel": "jio-1370",
    "title": "Silli Lalli",
    "subTitle": "Dr Vittal Rao, a doctor, and his politician wife deal with the mundane issues of life and engage in hilarious escapades with the rest of their family.",
    "image": "http://imagestataplay.whatsonindia.com/dasimages/genreimage/landscape/1280x720/26D59B8475F7A4100CF9D83FF9194D66FC385A3ET.jpg"
  },
  {
    "startRaw": "20251228013000",
    "stopRaw": "20251228033000",
    "start": "2025-12-28 07:00:00 IST",
    "stop": "2025-12-28 09:00:00 IST",
    "channel": "jio-1370",
    "title": "Bigg Boss Kannada",
    "subTitle": "Contestants from all walks of life compete with each other to win the cash prize while living in the house together under certain rules.",
    "image": "http://imagestataplay.whatsonindia.com/dasimages/genreimage/landscape/1280x720/26D59B8475F7A4100CF9D83FF9194D66FC385A3ET.jpg"
  },
  {
    "startRaw": "20251228033000",
    "stopRaw": "20251228050000",
    "start": "2025-12-28 09:00:00 IST",
    "stop": "2025-12-28 10:30:00 IST",
    "channel": "jio-1370",
    "title": "Bigg Boss Kannada",
    "subTitle": "Contestants from all walks of life compete with each other to win the cash prize while living in the house together under certain rules.",
    "image": "http://imagestataplay.whatsonindia.com/dasimages/genreimage/landscape/1280x720/26D59B8475F7A4100CF9D83FF9194D66FC385A3ET.jpg"
  },
  {
    "startRaw": "20251228050000",
    "stopRaw": "20251228063000",
    "start": "2025-12-28 10:30:00 IST",
    "stop": "2025-12-28 12:00:00 IST",
    "channel": "jio-1370",
    "title": "Bigg Boss Kannada",
    "subTitle": "Contestants from all walks of life compete with each other to win the cash prize while living in the house together under certain rules.",
    "image": "http://imagestataplay.whatsonindia.com/dasimages/genreimage/landscape/1280x720/26D59B8475F7A4100CF9D83FF9194D66FC385A3ET.jpg"
  },
  {
    "startRaw": "20251228063000",
    "stopRaw": "20251228080000",
    "start": "2025-12-28 12:00:00 IST",
    "stop": "2025-12-28 13:30:00 IST",
    "channel": "jio-1370",
    "title": "Bigg Boss Kannada",
    "subTitle": "Contestants from all walks of life compete with each other to win the cash prize while living in the house together under certain rules.",
    "image": "http://imagestataplay.whatsonindia.com/dasimages/genreimage/landscape/1280x720/26D59B8475F7A4100CF9D83FF9194D66FC385A3ET.jpg"
  },
  {
    "startRaw": "20251228080000",
    "stopRaw": "20251228093000",
    "start": "2025-12-28 13:30:00 IST",
    "stop": "2025-12-28 15:00:00 IST",
    "channel": "jio-1370",
    "title": "Bigg Boss Kannada",
    "subTitle": "Contestants from all walks of life compete with each other to win the cash prize while living in the house together under certain rules.",
    "image": "http://imagestataplay.whatsonindia.com/dasimages/genreimage/landscape/1280x720/26D59B8475F7A4100CF9D83FF9194D66FC385A3ET.jpg"
  },
  {
    "startRaw": "20251228093000",
    "stopRaw": "20251228113000",
    "start": "2025-12-28 15:00:00 IST",
    "stop": "2025-12-28 17:00:00 IST",
    "channel": "jio-1370",
    "title": "Bigg Boss Kannada",
    "subTitle": "Contestants from all walks of life compete with each other to win the cash prize while living in the house together under certain rules.",
    "image": "http://imagestataplay.whatsonindia.com/dasimages/genreimage/landscape/1280x720/26D59B8475F7A4100CF9D83FF9194D66FC385A3ET.jpg"
  },
  {
    "startRaw": "20251228113000",
    "stopRaw": "20251228123000",
    "start": "2025-12-28 17:00:00 IST",
    "stop": "2025-12-28 18:00:00 IST",
    "channel": "jio-1370",
    "title": "Mark Utsava",
    "subTitle": "",
    "image": "http://imagestataplay.whatsonindia.com/dasimages/genreimage/landscape/1280x720/26D59B8475F7A4100CF9D83FF9194D66FC385A3ET.jpg"
  },
  {
    "startRaw": "20251228123000",
    "stopRaw": "20251228130000",
    "start": "2025-12-28 18:00:00 IST",
    "stop": "2025-12-28 18:30:00 IST",
    "channel": "jio-1370",
    "title": "Yajamana",
    "subTitle": "A delivery boy, who is burdened with family responsibilities, gets into a contract marriage with Jhansi, a rich woman who despises men.",
    "image": "http://imagestataplay.whatsonindia.com/dasimages/genreimage/landscape/1280x720/26D59B8475F7A4100CF9D83FF9194D66FC385A3ET.jpg"
  },
  {
    "startRaw": "20251228130000",
    "stopRaw": "20251228133000",
    "start": "2025-12-28 18:30:00 IST",
    "stop": "2025-12-28 19:00:00 IST",
    "channel": "jio-1370",
    "title": "Yajamana",
    "subTitle": "A delivery boy, who is burdened with family responsibilities, gets into a contract marriage with Jhansi, a rich woman who despises men.",
    "image": "http://imagestataplay.whatsonindia.com/dasimages/genreimage/landscape/1280x720/26D59B8475F7A4100CF9D83FF9194D66FC385A3ET.jpg"
  },
  {
    "startRaw": "20251228133000",
    "stopRaw": "20251228140000",
    "start": "2025-12-28 19:00:00 IST",
    "stop": "2025-12-28 19:30:00 IST",
    "channel": "jio-1370",
    "title": "Bhagya Lakshmi",
    "subTitle": "Rishi blames Lakshmi for an accident, and she leaves with their daughter. Years later, their children meet, bringing Rishi and Lakshmi back into each other's lives.",
    "image": "http://imagestataplay.whatsonindia.com/dasimages/genreimage/landscape/1280x720/26D59B8475F7A4100CF9D83FF9194D66FC385A3ET.jpg"
  },
  {
    "startRaw": "20251228140000",
    "stopRaw": "20251228143000",
    "start": "2025-12-28 19:30:00 IST",
    "stop": "2025-12-28 20:00:00 IST",
    "channel": "jio-1370",
    "title": "Muddu Sose",
    "subTitle": "Vidya's dream of becoming a doctor is threatened when her father decides to get her married. Unfortunately, her father-in-law also believes that woman should not pursue education.",
    "image": "http://imagestataplay.whatsonindia.com/dasimages/genreimage/landscape/1280x720/26D59B8475F7A4100CF9D83FF9194D66FC385A3ET.jpg"
  },
  {
    "startRaw": "20251228143000",
    "stopRaw": "20251228150000",
    "start": "2025-12-28 20:00:00 IST",
    "stop": "2025-12-28 20:30:00 IST",
    "channel": "jio-1370",
    "title": "Sri Gandhada Gudi",
    "subTitle": "Chandana marries into a family with a troubled past in order to escape her fate. However, can she restore the family's hope?",
    "image": "http://imagestataplay.whatsonindia.com/dasimages/genreimage/landscape/1280x720/26D59B8475F7A4100CF9D83FF9194D66FC385A3ET.jpg"
  },
  {
    "startRaw": "20251228150000",
    "stopRaw": "20251228153000",
    "start": "2025-12-28 20:30:00 IST",
    "stop": "2025-12-28 21:00:00 IST",
    "channel": "jio-1370",
    "title": "Bhargavi LLB",
    "subTitle": "A lawyer fights against a powerful man, unaware that he will be her father-in-law in the future. As the lines blur between family and justice, she quickly finds herself at a crossroads.",
    "image": "http://imagestataplay.whatsonindia.com/dasimages/genreimage/landscape/1280x720/26D59B8475F7A4100CF9D83FF9194D66FC385A3ET.jpg"
  },
  {
    "startRaw": "20251228153000",
    "stopRaw": "20251228173000",
    "start": "2025-12-28 21:00:00 IST",
    "stop": "2025-12-28 23:00:00 IST",
    "channel": "jio-1370",
    "title": "Bigg Boss Kannada",
    "subTitle": "Contestants from all walks of life compete with each other to win the cash prize while living in the house together under certain rules.",
    "image": "http://imagestataplay.whatsonindia.com/dasimages/genreimage/landscape/1280x720/26D59B8475F7A4100CF9D83FF9194D66FC385A3ET.jpg"
  },
  {
    "startRaw": "20251228173000",
    "stopRaw": "20251228182959",
    "start": "2025-12-28 23:00:00 IST",
    "stop": "2025-12-28 23:59:59 IST",
    "channel": "jio-1370",
    "title": "Bigg Boss Kannada",
    "subTitle": "Contestants from all walks of life compete with each other to win the cash prize while living in the house together under certain rules.",
    "image": "http://imagestataplay.whatsonindia.com/dasimages/genreimage/landscape/1280x720/26D59B8475F7A4100CF9D83FF9194D66FC385A3ET.jpg"
  }
]